windmouse/__init__.py
windmouse/ahk_controller.py
windmouse/core.py
windmouse/pyautogui_controller.py
windmouse-1.0.2.dist-info/licenses/LICENSE
windmouse-1.0.2.dist-info/METADATA
windmouse-1.0.2.dist-info/WHEEL
windmouse-1.0.2.dist-info/top_level.txt
windmouse-1.0.2.dist-info/RECORD
