Metadata-Version: 2.4
Name: windmouse
Version: 1.0.2
Summary: Human-like mouse movement library implementing the WindMouse algorithm for bot detection avoidance
Author: WindMouse Contributors
License: GPL-3.0-only
Project-URL: Homepage, https://github.com/AsfhtgkDavid/windmouse
Project-URL: Documentation, https://windmouse.readthedocs.io
Project-URL: Repository, https://github.com/AsfhtgkDavid/windmouse
Project-URL: Issues, https://github.com/AsfhtgkDavid/windmouse/issues
Keywords: automation,mouse,windmouse,bot-detection,human-like
Classifier: Development Status :: 5 - Production/Stable
Classifier: Intended Audience :: Developers
Classifier: License :: OSI Approved :: GNU General Public License v3 (GPLv3)
Classifier: Programming Language :: Python :: 3
Classifier: Programming Language :: Python :: 3.10
Classifier: Programming Language :: Python :: 3.11
Classifier: Programming Language :: Python :: 3.12
Classifier: Topic :: Software Development :: Libraries :: Python Modules
Classifier: Topic :: Software Development :: Testing
Requires-Python: >=3.8
License-File: LICENSE
Requires-Dist: numpy>=1.22.0
Provides-Extra: ahk
Requires-Dist: ahk>=1.0.0; extra == "ahk"
Provides-Extra: pyautogui
Requires-Dist: pyautogui>=0.9.50; extra == "pyautogui"
Provides-Extra: all
Requires-Dist: ahk>=1.0.0; extra == "all"
Requires-Dist: pyautogui>=0.9.50; extra == "all"
Provides-Extra: docs
Requires-Dist: sphinx>=4.0.0; extra == "docs"
Requires-Dist: sphinx-rtd-theme>=1.0.0; extra == "docs"
Requires-Dist: sphinx-autodoc-typehints>=1.12.0; extra == "docs"
Dynamic: license-file
